tkgui/__init__.py
tkgui/tkgui.py
tkgui/tkgui_utils.py
tkgui-0.1.1.dist-info/LICENSE
tkgui-0.1.1.dist-info/METADATA
tkgui-0.1.1.dist-info/WHEEL
tkgui-0.1.1.dist-info/top_level.txt
tkgui-0.1.1.dist-info/RECORD
